openscm_twolayermodel/__init__.py
openscm_twolayermodel/_version.py
openscm_twolayermodel/base.py
openscm_twolayermodel/constants.py
openscm_twolayermodel/errors.py
openscm_twolayermodel/impulse_response_model.py
openscm_twolayermodel/two_layer_model.py
openscm_twolayermodel/utils.py
openscm_twolayermodel-0.2.3.dist-info/LICENSE
openscm_twolayermodel-0.2.3.dist-info/METADATA
openscm_twolayermodel-0.2.3.dist-info/WHEEL
openscm_twolayermodel-0.2.3.dist-info/top_level.txt
openscm_twolayermodel-0.2.3.dist-info/RECORD
