Metadata-Version: 2.1
Name: openscm-twolayermodel
Version: 0.2.3
Summary: Implementations of the two layer radiative forcing driven models by `Held et al. <https://journals.ametsoc.org/doi/full/10.1175/2009JCLI3466.1>`_ and `Geoffroy et al. <https://journals.ametsoc.org/doi/pdf/10.1175/JCLI-D-12-00195.1>`_
Home-page: https://github.com/openscm/openscm-twolayermodel
Author: Zeb Nicholls, Jared Lewis
Author-email: zebedee.nicholls@climate-energy-college.org, jared.lewis@climate-energy-college.org
License: 3-Clause BSD License
Keywords: openscm-twolayermodel,openscm,python,repo,simple,climate,model
Platform: UNKNOWN
Classifier: Development Status :: 4 - Beta
Classifier: License :: OSI Approved :: BSD License
Classifier: Intended Audience :: Developers
Classifier: Operating System :: OS Independent
Classifier: Programming Language :: Python :: 3.6
Classifier: Programming Language :: Python :: 3.7
Classifier: Programming Language :: Python :: 3.8
Classifier: Programming Language :: Python :: 3.9
Requires-Dist: scmdata (>=0.9)
Requires-Dist: tqdm
Provides-Extra: deploy
Requires-Dist: twine (>=1.11.0) ; extra == 'deploy'
Requires-Dist: setuptools (>=38.6.0) ; extra == 'deploy'
Requires-Dist: wheel (>=0.31.0) ; extra == 'deploy'
Provides-Extra: dev
Requires-Dist: bandit ; extra == 'dev'
Requires-Dist: black (==19.10b0) ; extra == 'dev'
Requires-Dist: black-nb ; extra == 'dev'
Requires-Dist: flake8 ; extra == 'dev'
Requires-Dist: isort (<5) ; extra == 'dev'
Requires-Dist: mypy ; extra == 'dev'
Requires-Dist: nbdime ; extra == 'dev'
Requires-Dist: pydocstyle ; extra == 'dev'
Requires-Dist: pylint (>=2.4.4) ; extra == 'dev'
Requires-Dist: twine (>=1.11.0) ; extra == 'dev'
Requires-Dist: setuptools (>=38.6.0) ; extra == 'dev'
Requires-Dist: wheel (>=0.31.0) ; extra == 'dev'
Requires-Dist: ipywidgets ; extra == 'dev'
Requires-Dist: notebook ; extra == 'dev'
Requires-Dist: seaborn ; extra == 'dev'
Requires-Dist: nbsphinx ; extra == 'dev'
Requires-Dist: sphinx (>=1.4) ; extra == 'dev'
Requires-Dist: sphinx-rtd-theme ; extra == 'dev'
Requires-Dist: sphinx-click ; extra == 'dev'
Requires-Dist: sphinx-copybutton ; extra == 'dev'
Requires-Dist: codecov ; extra == 'dev'
Requires-Dist: coverage ; extra == 'dev'
Requires-Dist: nbval ; extra == 'dev'
Requires-Dist: pytest-cov ; extra == 'dev'
Requires-Dist: pytest (>=4.0) ; extra == 'dev'
Requires-Dist: scipy ; extra == 'dev'
Provides-Extra: docs
Requires-Dist: ipywidgets ; extra == 'docs'
Requires-Dist: notebook ; extra == 'docs'
Requires-Dist: seaborn ; extra == 'docs'
Requires-Dist: nbsphinx ; extra == 'docs'
Requires-Dist: sphinx (>=1.4) ; extra == 'docs'
Requires-Dist: sphinx-rtd-theme ; extra == 'docs'
Requires-Dist: sphinx-click ; extra == 'docs'
Requires-Dist: sphinx-copybutton ; extra == 'docs'
Provides-Extra: notebooks
Requires-Dist: ipywidgets ; extra == 'notebooks'
Requires-Dist: notebook ; extra == 'notebooks'
Requires-Dist: seaborn ; extra == 'notebooks'
Provides-Extra: tests
Requires-Dist: codecov ; extra == 'tests'
Requires-Dist: coverage ; extra == 'tests'
Requires-Dist: nbval ; extra == 'tests'
Requires-Dist: pytest-cov ; extra == 'tests'
Requires-Dist: pytest (>=4.0) ; extra == 'tests'
Requires-Dist: scipy ; extra == 'tests'
